ai_cmd/__init__.py
ai_cmd/__main__.py
ai_cmd/ai/__init__.py
ai_cmd/ai/base.py
ai_cmd/ai/exceptions.py
ai_cmd/ai/services/__init__.py
ai_cmd/ai/services/mock.py
ai_cmd/ai/services/mock_reasoner.py
ai_cmd/ai/services/openai/__init__.py
ai_cmd/ai/services/openai/base.py
ai_cmd/ai/services/openai/mappers.py
ai_cmd/ai/types.py
ai_cmd/ajents/__init__.py
ai_cmd/ajents/assistant/__init__.py
ai_cmd/ajents/assistant/base.py
ai_cmd/ajents/assistant/const.py
ai_cmd/ajents/assistant/tools.py
ai_cmd/ajents/reasoner/__init__.py
ai_cmd/ajents/reasoner/base.py
ai_cmd/ajents/reasoner/const.py
ai_cmd/ajents/reasoner/pack.py
ai_cmd/app/__init__.py
ai_cmd/app/base.py
ai_cmd/app/commands/__init__.py
ai_cmd/app/commands/base.py
ai_cmd/app/commands/command_pack.py
ai_cmd/app/commands/commands_packs/__init__.py
ai_cmd/app/commands/commands_packs/config.py
ai_cmd/app/commands/commands_packs/history.py
ai_cmd/app/commands/commands_packs/system.py
ai_cmd/app/commands/const.py
ai_cmd/app/commands/events.py
ai_cmd/app/commands/parser.py
ai_cmd/app/const.py
ai_cmd/app/exceptions.py
ai_cmd/app/renders/__init__.py
ai_cmd/app/renders/tool_calls.py
ai_cmd/app/renders/tool_messages.py
ai_cmd/app/renders/utils.py
ai_cmd/app/styles.py
ai_cmd/app/types.py
ai_cmd/app/window.py
ai_cmd/controller/__init__.py
ai_cmd/controller/base.py
ai_cmd/controller/types.py
ai_cmd/controller/utils.py
ai_cmd/core/base.py
ai_cmd/core/events.py
ai_cmd/core/history/__init__.py
ai_cmd/core/history/base.py
ai_cmd/core/history/events.py
ai_cmd/core/history/types.py
ai_cmd/main.py
ai_cmd/settings/__init__.py
ai_cmd/settings/base.py
ai_cmd/settings/const.py
ai_cmd/settings/exceptions.py
ai_cmd/tools/__init__.py
ai_cmd/tools/base.py
ai_cmd/tools/events.py
ai_cmd/tools/schemas/__init__.py
ai_cmd/tools/schemas/generators.py
ai_cmd/tools/schemas/mapper.py
ai_cmd/tools/schemas/parsers.py
ai_cmd/tools/schemas/types.py
ai_cmd/tools/schemas/utils.py
ai_cmd/tools/tool_pack.py
ai_cmd/tools/tools_packs/__init__.py
ai_cmd-1.0.0.dist-info/LICENSE
ai_cmd-1.0.0.dist-info/METADATA
ai_cmd-1.0.0.dist-info/WHEEL
ai_cmd-1.0.0.dist-info/RECORD
