Metadata-Version: 2.3
Name: ai-cmd
Version: 1.0.0
Summary: Un asistente en tu terminal
License: MIT License
Author: Marlon
Author-email: 121285806+xmarlon30x2@users.noreply.github.com
Requires-Python: >=3.13
Classifier: License :: Other/Proprietary License
Classifier: Programming Language :: Python :: 3
Classifier: Programming Language :: Python :: 3.13
Requires-Dist: openai (>=1.66.2,<2.0.0)
Requires-Dist: pexpect (>=4.9.0,<5.0.0)
Requires-Dist: prompt-toolkit (>=3.0.50,<4.0.0)
Requires-Dist: rich (>=13.9.4,<14.0.0)
